{"BaseModel.5e663b39-564e-4c0d-92c6-9a455f822a03": {"id": "5e663b39-564e-4c0d-92c6-9a455f822a03", "created_at": "2023-11-10T18:26:24.629057", "updated_at": "2023-11-10T18:26:24.629065", "name": "My_First_Model", "my_number": 89, "update_at": "2023-11-10T18:26:24.629115", "__class__": "BaseModel"}, "BaseModel.3f0dd3a2-099d-4a9f-b192-bdba05ee3ea2": {"id": "3f0dd3a2-099d-4a9f-b192-bdba05ee3ea2", "created_at": "2023-11-10T18:28:40.295038", "updated_at": "2023-11-10T18:28:40.295040", "name": "My_First_Model", "my_number": 89, "update_at": "2023-11-10T18:28:40.295069", "__class__": "BaseModel"}}